{
  "title": "How to use",
  "slug": "how-to-use",
  "content": {
    "data": {},
    "content": [
      {
        "data": {},
        "content": [
          {
            "data": {},
            "marks": [],
            "value": "Lorem Ipsum",
            "nodeType": "text"
          }
        ],
        "nodeType": "heading-4"
      },
      {
        "data": {},
        "content": [
          {
            "data": {},
            "marks": [],
            "value": "Lorem property ownership mapping Lorem ipsum dolor sit amet, consectetur adipiscing elit, sed do eiusmod tempor incididunt ut labore et dolore magna aliqua. Ut enim ad minim veniam, quis nost ",
            "nodeType": "text"
          },
          {
            "data": {
              "uri": "http://www1.nyc.gov/site/hpd/about/open-data.page"
            },
            "content": [
              {
                "data": {},
                "marks": [],
                "value": "HPD registration data",
                "nodeType": "text"
              }
            ],
            "nodeType": "hyperlink"
          },
          {
            "data": {},
            "marks": [],
            "value": " buildings.",
            "nodeType": "text"
          }
        ],
        "nodeType": "paragraph"
      },
      {
        "data": {},
        "content": [
          {
            "data": {},
            "marks": [],
            "value": "Duis aute irure dolor in reprehenderit:",
            "nodeType": "text"
          }
        ],
        "nodeType": "paragraph"
      },
      {
        "data": {},
        "content": [
          {
            "data": {},
            "content": [
              {
                "data": {},
                "content": [
                  {
                    "data": {},
                    "marks": [],
                    "value": "r magni dolores eos qui ratione voluptatem sequi nesciunt. Neque porro quisquam est, qui dolorem ipsum quia dolor sit amet, consectetur, adipisci velit, sed quia non numquam eius modi tempora incidunt ut labore et dolore magnam aliquam quaerat voluptatem. Ut",
                    "nodeType": "text"
                  }
                ],
                "nodeType": "paragraph"
              }
            ],
            "nodeType": "list-item"
          },
          {
            "data": {},
            "content": [
              {
                "data": {},
                "content": [
                  {
                    "data": {},
                    "marks": [],
                    "value": "minima veniam, quis nostrum exercitationem ullam corporis suscipit laboriosam, nisi ut aliquid ex ea commodi consequatur? Quis aute",
                    "nodeType": "text"
                  }
                ],
                "nodeType": "paragraph"
              }
            ],
            "nodeType": "list-item"
          }
        ],
        "nodeType": "ordered-list"
      },
      {
        "data": {},
        "content": [
          {
            "data": {},
            "marks": [],
            "value": "",
            "nodeType": "text"
          }
        ],
        "nodeType": "paragraph"
      }
    ],
    "nodeType": "document"
  }
}